psmlc/ABOUT
psmlc/CHANGELOG.md
psmlc/LICENSE
psmlc/PSML.py
psmlc/README.md
psmlc/VERSION
psmlc/__init__.py
psmlc/__main__.py
psmlc/auto.js
psmlc/bottle.py
psmlc/install.sh
psmlc/precompiled.psml
psmlc/psml.1
psmlc/psml.html
psmlc/psml.py
psmlc/psml_web.py
psmlc/test.psml
psmlc/Documents/ERR.txt
psmlc/Documents/NS2PS.txt
psmlc/Documents/PS2NS.txt
psmlc/Documents/_check_ver.txt
psmlc/Documents/change_script.txt
psmlc/Documents/change_style.txt
psmlc/Documents/compile.txt
psmlc/Documents/configinit.txt
psmlc/Documents/del_page.txt
psmlc/Documents/editconf.txt
psmlc/Documents/endpage.txt
psmlc/Documents/fcompile.txt
psmlc/Documents/getpage.txt
psmlc/Documents/initialize_page.txt
psmlc/Documents/initialize_route.txt
psmlc/Documents/initialize_server.txt
psmlc/Documents/run_server.txt
psmlc/Documents/showman.txt
psmlc/Documents/up.txt
psmlc/Documents/upgrade.txt
psmlc/Documents/vercomp.txt
psmlc/obj/UbuntuMono.ttf
psmlc/obj/__init__.css
psmlc-1.4.2.dist-info/LICENSE
psmlc-1.4.2.dist-info/METADATA
psmlc-1.4.2.dist-info/WHEEL
psmlc-1.4.2.dist-info/entry_points.txt
psmlc-1.4.2.dist-info/top_level.txt
psmlc-1.4.2.dist-info/RECORD
