Metadata-Version: 2.1
Name: psmlc
Version: 1.4.2
Summary: A simpile python server markup language
Home-page: https://github.com/lone-air/psml
Author: Lone_air
Author-email: Lone_air_Use@outlook.com
License: GPLv2.0
Platform: UNKNOWN
Requires-Python: >=3.6
Requires-Dist: beaker
Requires-Dist: bottle
Requires-Dist: flask
